Workbook

Sheet Assumptions
A1: BRICLY — MODEL ASSUMPTIONS (high-ticket pricing)
A2: Blue cells are inputs. Change these to flex the model.
A4: PRICING (per customer, annual)
A5: Annual platform license | B5: 10000 | C5: Includes CRM + Studio + onboarding + 1 development
A6: Per additional development | B6: 1500 | C6: Each development beyond the first
A7: Per unit (flat, decoupled from sale price) | B7: 200 | C7: Full sales pipeline + buyer packs per unit
A8: Minimum annual commitment | B8: 25000 | C8: Screens sub-scale buyers
A10: SEGMENT MIX & ACV
A11: Small developer — share | B11: 0.5 | C11: ~6 small developments/yr, ~60 units
A12: Small developer — ACV | B12: 29500 | C12: 10k + 5x1.5k + 60x200
A13: Mid developer — share | B13: 0.35 | C13: ~6 medium developments/yr, ~210 units
A14: Mid developer — ACV | B14: 59500 | C14: 10k + 5x1.5k + 210x200
A15: Large developer — share | B15: 0.15 | C15: ~2 large developments/yr, ~250 units
A16: Large developer — ACV | B16: 61500 | C16: 10k + 1x1.5k + 250x200
A17: BLENDED ACV | B17: =B11*B12+B13*B14+B15*B16 -> 44800 | C17: Weighted average ACV
A19: COGS (per customer, annual)
A20: Generation (renders, brand, microsite, video) | B20: 876 | C20: Episodic, blended across segments
A21: AI layer (CRM chat + consulting via Claude) | B21: 3560 | C21: Recurring, scales with active users
A22: Infrastructure (allocated) | B22: 1350 | C22: Neon, Vercel, Trigger.dev, storage, etc.
A23: COGS ex-payments (per customer/yr) | B23: =B20+B21+B22 -> 5786 | C23: Sum of the three above
A24: Payment processing (% of revenue) | B24: 0.025 | C24: PSP fees
A25: BLENDED GROSS MARGIN | B25: =1-(B23/B17+B24) -> 0.84584821 | C25: 1 - (COGS ex-pay / ACV + payment rate)
A27: GROWTH & EFFICIENCY
A28: Monthly gross revenue per customer | B28: =B17/12 -> 3733.3333 | C28: Blended ACV / 12
A29: CAC (blended, demo-gated enterprise) | B29: 6000 | C29: Demand gen + partial sales allocation
A30: Monthly gross profit per customer | B30: =B28*B25 -> 3157.8333 | C30: For payback / LTV
A31: Payback period (months) | B31: =B29/B30 -> 1.9000369 | C31: CAC / monthly gross profit
A32: Monthly churn | B32: 0.015 | C32: Enterprise, sticky; conservative
A33: Avg client lifetime (months) | B33: =1/B32 -> 66.666667 | C33: 1 / monthly churn
A34: LTV | B34: =B30*B33 -> 210522.22 | C34: Monthly gross profit x lifetime
A35: LTV : CAC | B35: =B34/B29 -> 35.087037 | C35: >10x is world-class

Sheet Pricing Model
A1: BRICLY — PRICING MODEL (high-ticket, demo-gated, annual)
A2: Supersedes the €99 base + €5/unit/month model. No public pricing. Unlimited users.
A4: THE THREE LEVERS
A5: Annual platform license | B5: =Assumptions!B5 -> 10000 | E5: CRM + Studio + onboarding + first development
A6: Per additional development | B6: =Assumptions!B6 -> 1500 | E6: Constraint model, brand, microsite, base allowance
A7: Per unit (flat) | B7: =Assumptions!B7 -> 200 | E7: Sales pipeline + buyer packs; not priced on renders
A8: Minimum annual commitment | B8: =Assumptions!B8 -> 25000 | E8: Floor that screens sub-scale buyers
A10: ILLUSTRATIVE ACV BY CUSTOMER PROFILE
A11: Profile | B11: Developments/yr | C11: Units/yr | D11: ACV | E11: Notes
A12: Small developer | B12: 6 small | C12: ~60 | D12: =Assumptions!B12 -> 29500 | E12: 10k + 5x1.5k + 60x200
A13: Mid developer | B13: 6 medium | C13: ~210 | D13: =Assumptions!B14 -> 59500 | E13: 10k + 5x1.5k + 210x200
A14: Large developer | B14: 2 large | C14: ~250 | D14: =Assumptions!B16 -> 61500 | E14: 10k + 1x1.5k + 250x200
A16: Blended ACV (mix-weighted) | D16: =Assumptions!B17 -> 44800
A18: INCLUDED GENERATION ALLOWANCE PER DEVELOPMENT
A19: Standard (up to ~50 units) | B19: 6 layouts of renders, all standard buyer packs, 1 microsite, 1 walkthrough, 10 ad creatives
A20: Large (50+ units) | B20: As standard + expanded external close-ups + up to 3 walkthroughs
A21: Top-ups | B21: Additional layouts + heavy custom buyer-render intensity. Sold in output blocks, auto-replenish.

Sheet Unit Economics
A1: BRICLY — UNIT ECONOMICS & PAYBACK
A3: PER-CUSTOMER ECONOMICS BY SEGMENT
A4: Metric | B4: Small | C4: Mid | D4: Large | E4: Blended | F4: Notes
A5: ACV | B5: =Assumptions!B12 -> 29500 | C5: =Assumptions!B14 -> 59500 | D5: =Assumptions!B16 -> 61500 | E5: =Assumptions!B17 -> 44800 | F5: Annual contract value
A6: Generation COGS | B6: 660 | C6: 1110 | D6: 1050 | E6: =Assumptions!B20 -> 876
A7: AI layer COGS (chat + consulting) | B7: 2400 | C7: 4000 | D7: 6400 | E7: =Assumptions!B21 -> 3560 | F7: Scales with active users
A8: Infrastructure | B8: 1200 | C8: 1500 | D8: 1500 | E8: =Assumptions!B22 -> 1350
A9: Payment processing | B9: =B5*Assumptions!$B$24 -> 737.5 | C9: =C5*Assumptions!$B$24 -> 1487.5 | D9: =D5*Assumptions!$B$24 -> 1537.5 | E9: =E5*Assumptions!$B$24 -> 1120
A10: Total COGS | B10: =SUM(B6:B9) -> 4997.5 | C10: =SUM(C6:C9) -> 8097.5 | D10: =SUM(D6:D9) -> 10487.5 | E10: =SUM(E6:E9) -> 6906
A11: Gross profit | B11: =B5-B10 -> 24502.5 | C11: =C5-C10 -> 51402.5 | D11: =D5-D10 -> 51012.5 | E11: =E5-E10 -> 37894
A12: Gross margin | B12: =B11/B5 -> 0.83059322 | C12: =C11/C5 -> 0.86390756 | D12: =D11/D5 -> 0.82947154 | E12: =E11/E5 -> 0.84584821
A14: BLENDED ACQUISITION & LIFETIME
A15: Blended ACV | B15: =Assumptions!B17 -> 44800 | F15: Mix-weighted
A16: Blended gross margin | B16: =Assumptions!B25 -> 0.84584821 | F16: After all COGS incl. AI layer
A17: Monthly gross profit / customer | B17: =Assumptions!B30 -> 3157.8333 | F17: Drives payback
A18: CAC | B18: =Assumptions!B29 -> 6000 | F18: Demo-gated enterprise
A19: Payback period | B19: =Assumptions!B31 -> 1.9000369 | F19: Months to recover CAC
A20: Avg client lifetime | B20: =Assumptions!B33 -> 66.666667 | F20: Months (1 / churn)
A21: LTV | B21: =Assumptions!B34 -> 210522.22 | F21: Gross profit over lifetime
A22: LTV : CAC | B22: =Assumptions!B35 -> 35.087037 | F22: World-class >10x
A24: NOTE ON ARR COMPOSITION
A25: Hard recurring (platform licenses) is ~22% of revenue; per-development and per-unit are usage-based but recur as developers continuously launch. State the split with investors.

Sheet P&L Monthly
A1: BRICLY — MONTHLY P&L | high-ticket model | €5M ARR target end of Year 2
A2: Line item | C2: Y1M01▸B | D2: Y1M02▸B | E2: Y1M03▸B | F2: Y1M04▸B | G2: Y1M05▸B | H2: Y1M06▸$ | I2: Y1M07 | J2: Y1M08 | K2: Y1M09 | L2: Y1M10 | M2: Y1M11 | N2: Y1M12 | O2: Y2M01 | P2: Y2M02 | Q2: Y2M03 | R2: Y2M04 | S2: Y2M05 | T2: Y2M06 | U2: Y2M07 | V2: Y2M08 | W2: Y2M09 | X2: Y2M10 | Y2: Y2M11 | Z2: Y2M12 | AA2: Y3M01 | AB2: Y3M02 | AC2: Y3M03 | AD2: Y3M04 | AE2: Y3M05 | AF2: Y3M06 | AG2: Y3M07 | AH2: Y3M08 | AI2: Y3M09 | AJ2: Y3M10 | AK2: Y3M11 | AL2: Y3M12
A3: REVENUE & GROSS PROFIT (▸B build phase · ▸$ first revenue M6)
A4: Gross Revenue | C4: =C42*Assumptions!$B$28 -> 0 | D4: =D42*Assumptions!$B$28 -> 0 | E4: =E42*Assumptions!$B$28 -> 0 | F4: =F42*Assumptions!$B$28 -> 0 | G4: =G42*Assumptions!$B$28 -> 0 | H4: =H42*Assumptions!$B$28 -> 14933.333 | I4: =I42*Assumptions!$B$28 -> 26133.333 | J4: =J42*Assumptions!$B$28 -> 37333.333 | ... AL4: =AL42*Assumptions!$B$28 -> 653333.33
A6: COGS — Generation + AI layer + Infra | C6: =-C42*Assumptions!$B$23/12 -> 0 | D6: =-D42*Assumptions!$B$23/12 -> 0 | E6: =-E42*Assumptions!$B$23/12 -> 0 | F6: =-F42*Assumptions!$B$23/12 -> 0 | G6: =-G42*Assumptions!$B$23/12 -> 0 | H6: =-H42*Assumptions!$B$23/12 -> -1928.6667 | I6: =-I42*Assumptions!$B$23/12 -> -3375.1667 | J6: =-J42*Assumptions!$B$23/12 -> -4821.6667 | ... AL6: =-AL42*Assumptions!$B$23/12 -> -84379.167
A7: COGS — Payment processing | C7: =-C4*Assumptions!$B$24 -> 0 | D7: =-D4*Assumptions!$B$24 -> 0 | E7: =-E4*Assumptions!$B$24 -> 0 | F7: =-F4*Assumptions!$B$24 -> 0 | G7: =-G4*Assumptions!$B$24 -> 0 | H7: =-H4*Assumptions!$B$24 -> -373.33333 | I7: =-I4*Assumptions!$B$24 -> -653.33333 | J7: =-J4*Assumptions!$B$24 -> -933.33333 | ... AL7: =-AL4*Assumptions!$B$24 -> -16333.333
A8: TOTAL COGS | C8: =C6+C7 -> 0 | D8: =D6+D7 -> 0 | E8: =E6+E7 -> 0 | F8: =F6+F7 -> 0 | G8: =G6+G7 -> 0 | H8: =H6+H7 -> -2302 | I8: =I6+I7 -> -4028.5 | J8: =J6+J7 -> -5755 | ... AL8: =AL6+AL7 -> -100712.5
A9: GROSS PROFIT | C9: =C4+C8 -> 0 | D9: =D4+D8 -> 0 | E9: =E4+E8 -> 0 | F9: =F4+F8 -> 0 | G9: =G4+G8 -> 0 | H9: =H4+H8 -> 12631.333 | I9: =I4+I8 -> 22104.833 | J9: =J4+J8 -> 31578.333 | ... AL9: =AL4+AL8 -> 552620.83
A11: PAYROLL (15% employer overhead included; +3%/yr from Y2)
A12: Founder Salary (M8) | C12: 0 | D12: 0 | E12: 0 | F12: 0 | G12: 0 | H12: 0 | I12: 0 | J12: -3450 | K12: -3450 | L12: -3450 | M12: -3450 | N12: -3450 | O12: -3554 | P12: -3554 | Q12: -3554 | R12: -3554 | S12: -3554 | T12: -3554 | U12: -3554 | V12: -3554 | W12: -3554 | X12: -3554 | Y12: -3554 | Z12: -3554 | AA12: -3660 | AB12: -3660 | AC12: -3660 | AD12: -3660 | AE12: -3660 | AF12: -3660 | AG12: -3660 | AH12: -3660 | AI12: -3660 | AJ12: -3660 | AK12: -3660 | AL12: -3660
A13: Lead Developer — Senior AI Fullstack (M1) | C13: -9583 | D13: -9583 | E13: -9583 | F13: -9583 | G13: -9583 | H13: -9583 | I13: -9583 | J13: -9583 | K13: -9583 | L13: -9583 | M13: -9583 | N13: -9583 | O13: -9870 | P13: -9870 | Q13: -9870 | R13: -9870 | S13: -9870 | T13: -9870 | U13: -9870 | V13: -9870 | W13: -9870 | X13: -9870 | Y13: -9870 | Z13: -9870 | AA13: -10167 | AB13: -10167 | AC13: -10167 | AD13: -10167 | AE13: -10167 | AF13: -10167 | AG13: -10167 | AH13: -10167 | AI13: -10167 | AJ13: -10167 | AK13: -10167 | AL13: -10167
A14: Developer 2 — Mid AI Fullstack (M2) | C14: 0 | D14: -6229 | E14: -6229 | F14: -6229 | G14: -6229 | H14: -6229 | I14: -6229 | J14: -6229 | K14: -6229 | L14: -6229 | M14: -6229 | N14: -6229 | O14: -6416 | P14: -6416 | Q14: -6416 | R14: -6416 | S14: -6416 | T14: -6416 | U14: -6416 | V14: -6416 | W14: -6416 | X14: -6416 | Y14: -6416 | Z14: -6416 | AA14: -6608 | AB14: -6608 | AC14: -6608 | AD14: -6608 | AE14: -6608 | AF14: -6608 | AG14: -6608 | AH14: -6608 | AI14: -6608 | AJ14: -6608 | AK14: -6608 | AL14: -6608
A15: Developer 3 — Mid AI Fullstack (M13) | C15: 0 | D15: 0 | E15: 0 | F15: 0 | G15: 0 | H15: 0 | I15: 0 | J15: 0 | K15: 0 | L15: 0 | M15: 0 | N15: 0 | O15: -6416 | P15: -6416 | Q15: -6416 | R15: -6416 | S15: -6416 | T15: -6416 | U15: -6416 | V15: -6416 | W15: -6416 | X15: -6416 | Y15: -6416 | Z15: -6416 | AA15: -6608 | AB15: -6608 | AC15: -6608 | AD15: -6608 | AE15: -6608 | AF15: -6608 | AG15: -6608 | AH15: -6608 | AI15: -6608 | AJ15: -6608 | AK15: -6608 | AL15: -6608
A16: Developer 4 — Scale (M22) | C16: 0 | D16: 0 | E16: 0 | F16: 0 | G16: 0 | H16: 0 | I16: 0 | J16: 0 | K16: 0 | L16: 0 | M16: 0 | N16: 0 | O16: 0 | P16: 0 | Q16: 0 | R16: 0 | S16: 0 | T16: 0 | U16: 0 | V16: 0 | W16: 0 | X16: -6416 | Y16: -6416 | Z16: -6416 | AA16: -6608 | AB16: -6608 | AC16: -6608 | AD16: -6608 | AE16: -6608 | AF16: -6608 | AG16: -6608 | AH16: -6608 | AI16: -6608 | AJ16: -6608 | AK16: -6608 | AL16: -6608
A17: UX/UI Designer Phase 1 — M1-M6 | C17: -5000 | D17: -5000 | E17: -5000 | F17: -5000 | G17: -5000 | H17: -5000 | I17: 0 | J17: 0 | K17: 0 | L17: 0 | M17: 0 | N17: 0 | O17: 0 | P17: 0 | Q17: 0 | R17: 0 | S17: 0 | T17: 0 | U17: 0 | V17: 0 | W17: 0 | X17: 0 | Y17: 0 | Z17: 0 | AA17: 0 | AB17: 0 | AC17: 0 | AD17: 0 | AE17: 0 | AF17: 0 | AG17: 0 | AH17: 0 | AI17: 0 | AJ17: 0 | AK17: 0 | AL17: 0
A18: UX/UI Designer Phase 2 — M7+ | C18: 0 | D18: 0 | E18: 0 | F18: 0 | G18: 0 | H18: 0 | I18: -3000 | J18: -3000 | K18: -3000 | L18: -3000 | M18: -3000 | N18: -3000 | O18: -3090 | P18: -3090 | Q18: -3090 | R18: -3090 | S18: -3090 | T18: -3090 | U18: -3090 | V18: -3090 | W18: -3090 | X18: -3090 | Y18: -3090 | Z18: -3090 | AA18: -3183 | AB18: -3183 | AC18: -3183 | AD18: -3183 | AE18: -3183 | AF18: -3183 | AG18: -3183 | AH18: -3183 | AI18: -3183 | AJ18: -3183 | AK18: -3183 | AL18: -3183
A19: Content Creator (M1) | C19: -2300 | D19: -2300 | E19: -2300 | F19: -2300 | G19: -2300 | H19: -2300 | I19: -2300 | J19: -2300 | K19: -2300 | L19: -2300 | M19: -2300 | N19: -2300 | O19: -2369 | P19: -2369 | Q19: -2369 | R19: -2369 | S19: -2369 | T19: -2369 | U19: -2369 | V19: -2369 | W19: -2369 | X19: -2369 | Y19: -2369 | Z19: -2369 | AA19: -2440 | AB19: -2440 | AC19: -2440 | AD19: -2440 | AE19: -2440 | AF19: -2440 | AG19: -2440 | AH19: -2440 | AI19: -2440 | AJ19: -2440 | AK19: -2440 | AL19: -2440
A20: Sales Executive 1 (M9) | C20: 0 | D20: 0 | E20: 0 | F20: 0 | G20: 0 | H20: 0 | I20: 0 | J20: 0 | K20: -3067 | L20: -3067 | M20: -3067 | N20: -3067 | O20: -3159 | P20: -3159 | Q20: -3159 | R20: -3159 | S20: -3159 | T20: -3159 | U20: -3159 | V20: -3159 | W20: -3159 | X20: -3159 | Y20: -3159 | Z20: -3159 | AA20: -3254 | AB20: -3254 | AC20: -3254 | AD20: -3254 | AE20: -3254 | AF20: -3254 | AG20: -3254 | AH20: -3254 | AI20: -3254 | AJ20: -3254 | AK20: -3254 | AL20: -3254
A21: Sales Executive 2 — Scale (M22) | C21: 0 | D21: 0 | E21: 0 | F21: 0 | G21: 0 | H21: 0 | I21: 0 | J21: 0 | K21: 0 | L21: 0 | M21: 0 | N21: 0 | O21: 0 | P21: 0 | Q21: 0 | R21: 0 | S21: 0 | T21: 0 | U21: 0 | V21: 0 | W21: 0 | X21: -3159 | Y21: -3159 | Z21: -3159 | AA21: -3254 | AB21: -3254 | AC21: -3254 | AD21: -3254 | AE21: -3254 | AF21: -3254 | AG21: -3254 | AH21: -3254 | AI21: -3254 | AJ21: -3254 | AK21: -3254 | AL21: -3254
A22: Customer Success Manager (M13) | C22: 0 | D22: 0 | E22: 0 | F22: 0 | G22: 0 | H22: 0 | I22: 0 | J22: 0 | K22: 0 | L22: 0 | M22: 0 | N22: 0 | O22: -2961 | P22: -2961 | Q22: -2961 | R22: -2961 | S22: -2961 | T22: -2961 | U22: -2961 | V22: -2961 | W22: -2961 | X22: -2961 | Y22: -2961 | Z22: -2961 | AA22: -3050 | AB22: -3050 | AC22: -3050 | AD22: -3050 | AE22: -3050 | AF22: -3050 | AG22: -3050 | AH22: -3050 | AI22: -3050 | AJ22: -3050 | AK22: -3050 | AL22: -3050
A23: Marketing Executive — Paid Ads (M17) | C23: 0 | D23: 0 | E23: 0 | F23: 0 | G23: 0 | H23: 0 | I23: 0 | J23: 0 | K23: 0 | L23: 0 | M23: 0 | N23: 0 | O23: 0 | P23: 0 | Q23: 0 | R23: 0 | S23: -3751 | T23: -3751 | U23: -3751 | V23: -3751 | W23: -3751 | X23: -3751 | Y23: -3751 | Z23: -3751 | AA23: -3864 | AB23: -3864 | AC23: -3864 | AD23: -3864 | AE23: -3864 | AF23: -3864 | AG23: -3864 | AH23: -3864 | AI23: -3864 | AJ23: -3864 | AK23: -3864 | AL23: -3864
A24: TOTAL PAYROLL | C24: =SUM(C12:C23) -> -16883 | D24: =SUM(D12:D23) -> -23112 | E24: =SUM(E12:E23) -> -23112 | F24: =SUM(F12:F23) -> -23112 | G24: =SUM(G12:G23) -> -23112 | H24: =SUM(H12:H23) -> -23112 | I24: =SUM(I12:I23) -> -21112 | J24: =SUM(J12:J23) -> -24562 | ... AL24: =SUM(AL12:AL23) -> -52696
A26: OPERATING COSTS
A27: Software stack (Neon, Vercel, Trigger.dev, etc.) | C27: -950 | D27: -950 | E27: -950 | F27: -950 | G27: -950 | H27: -950 | I27: -950 | J27: -950 | K27: -950 | L27: -950 | M27: -950 | N27: -950 | O27: -950 | P27: -950 | Q27: -950 | R27: -950 | S27: -950 | T27: -950 | U27: -950 | V27: -950 | W27: -950 | X27: -950 | Y27: -950 | Z27: -950 | AA27: -950 | AB27: -950 | AC27: -950 | AD27: -950 | AE27: -950 | AF27: -950 | AG27: -950 | AH27: -950 | AI27: -950 | AJ27: -950 | AK27: -950 | AL27: -950
A28: Demand gen / paid acquisition (from M8) | C28: 0 | D28: 0 | E28: 0 | F28: 0 | G28: 0 | H28: 0 | I28: 0 | J28: -1000 | K28: -1000 | L28: -2000 | M28: -3000 | N28: -4000 | O28: -8000 | P28: -8000 | Q28: -8000 | R28: -8000 | S28: -8000 | T28: -8000 | U28: -8000 | V28: -8000 | W28: -8000 | X28: -8000 | Y28: -8000 | Z28: -8000 | AA28: -15000 | AB28: -15000 | AC28: -15000 | AD28: -15000 | AE28: -15000 | AF28: -15000 | AG28: -20000 | AH28: -20000 | AI28: -20000 | AJ28: -20000 | AK28: -20000 | AL28: -20000
A29: Office — Malta HQ | C29: -1200 | D29: -1200 | E29: -1200 | F29: -1200 | G29: -1200 | H29: -1200 | I29: -1200 | J29: -1200 | K29: -1200 | L29: -1200 | M29: -1200 | N29: -1200 | O29: -1200 | P29: -1200 | Q29: -1200 | R29: -1200 | S29: -1200 | T29: -1200 | U29: -1200 | V29: -1200 | W29: -1200 | X29: -1200 | Y29: -1200 | Z29: -1200 | AA29: -1200 | AB29: -1200 | AC29: -1200 | AD29: -1200 | AE29: -1200 | AF29: -1200 | AG29: -1200 | AH29: -1200 | AI29: -1200 | AJ29: -1200 | AK29: -1200 | AL29: -1200
A30: Legal, accounting & compliance | C30: -500 | D30: -500 | E30: -500 | F30: -500 | G30: -500 | H30: -500 | I30: -500 | J30: -500 | K30: -800 | L30: -800 | M30: -800 | N30: -800 | O30: -800 | P30: -800 | Q30: -800 | R30: -800 | S30: -800 | T30: -800 | U30: -800 | V30: -800 | W30: -800 | X30: -800 | Y30: -800 | Z30: -800 | AA30: -800 | AB30: -800 | AC30: -800 | AD30: -800 | AE30: -800 | AF30: -800 | AG30: -800 | AH30: -800 | AI30: -800 | AJ30: -800 | AK30: -800 | AL30: -800
A31: Conferences & industry events | C31: 0 | D31: 0 | E31: 0 | F31: 0 | G31: 0 | H31: 0 | I31: 0 | J31: 0 | K31: 0 | L31: -3000 | M31: 0 | N31: 0 | O31: 0 | P31: 0 | Q31: 0 | R31: 0 | S31: 0 | T31: -3000 | U31: 0 | V31: 0 | W31: 0 | X31: 0 | Y31: 0 | Z31: -3000 | AA31: 0 | AB31: 0 | AC31: 0 | AD31: 0 | AE31: 0 | AF31: -3000 | AG31: 0 | AH31: 0 | AI31: 0 | AJ31: 0 | AK31: 0 | AL31: -3000
A32: Misc & contingency (1.5% of revenue) | C32: =-C4*0.015 -> 0 | D32: =-D4*0.015 -> 0 | E32: =-E4*0.015 -> 0 | F32: =-F4*0.015 -> 0 | G32: =-G4*0.015 -> 0 | H32: =-H4*0.015 -> -224 | I32: =-I4*0.015 -> -392 | J32: =-J4*0.015 -> -560 | ... AL32: =-AL4*0.015 -> -9800
A33: TOTAL OPEX | C33: =SUM(C27:C32) -> -2650 | D33: =SUM(D27:D32) -> -2650 | E33: =SUM(E27:E32) -> -2650 | F33: =SUM(F27:F32) -> -2650 | G33: =SUM(G27:G32) -> -2650 | H33: =SUM(H27:H32) -> -2874 | I33: =SUM(I27:I32) -> -3042 | J33: =SUM(J27:J32) -> -4210 | ... AL33: =SUM(AL27:AL32) -> -35750
A35: SUMMARY
A36: TOTAL COSTS | C36: =C24+C33 -> -19533 | D36: =D24+D33 -> -25762 | E36: =E24+E33 -> -25762 | F36: =F24+F33 -> -25762 | G36: =G24+G33 -> -25762 | H36: =H24+H33 -> -25986 | I36: =I24+I33 -> -24154 | J36: =J24+J33 -> -28772 | ... AL36: =AL24+AL33 -> -88446
A37: EBITDA | C37: =C9+C36 -> -19533 | D37: =D9+D36 -> -25762 | E37: =E9+E36 -> -25762 | F37: =F9+F36 -> -25762 | G37: =G9+G36 -> -25762 | H37: =H9+H36 -> -13354.667 | I37: =I9+I36 -> -2049.1667 | J37: =J9+J36 -> 2806.3333 | ... AL37: =AL9+AL36 -> 464174.83
A38: EBITDA margin | C38: =IF(C4=0,0,C37/C4) -> 0 | D38: =IF(D4=0,0,D37/D4) -> 0 | E38: =IF(E4=0,0,E37/E4) -> 0 | F38: =IF(F4=0,0,F37/F4) -> 0 | G38: =IF(G4=0,0,G37/G4) -> 0 | H38: =IF(H4=0,0,H37/H4) -> -0.89428571 | I38: =IF(I4=0,0,I37/I4) -> -0.07841199 | J38: =IF(J4=0,0,J37/J4) -> 0.075169643 | ... AL38: =IF(AL4=0,0,AL37/AL4) -> 0.71047168
A39: Cumulative cash position | C39: =C37 -> -19533 | D39: =C39+D37 -> -45295 | E39: =D39+E37 -> -71057 | F39: =E39+F37 -> -96819 | G39: =F39+G37 -> -122581 | H39: =G39+H37 -> -135935.67 | I39: =H39+I37 -> -137984.83 | J39: =I39+J37 -> -135178.5 | K39: =J39+K37 -> -126433.67 | ... AL39: =AK39+AL37 -> 6505412
A41: KPIs
A42: Active customers | C42: 0 | D42: 0 | E42: 0 | F42: 0 | G42: 0 | H42: 4 | I42: 7 | J42: 10 | K42: 13 | L42: 16 | M42: 20 | N42: 24 | O42: 29 | P42: 35 | Q42: 41 | R42: 47 | S42: 54 | T42: 61 | U42: 68 | V42: 76 | W42: 84 | X42: 92 | Y42: 101 | Z42: 112 | AA42: 120 | AB42: 126 | AC42: 132 | AD42: 138 | AE42: 144 | AF42: 150 | AG42: 155 | AH42: 160 | AI42: 165 | AJ42: 169 | AK42: 172 | AL42: 175
A43: Net new customers | C43: 0 | D43: 0 | E43: 0 | F43: 0 | G43: 0 | H43: 4 | I43: 3 | J43: 3 | K43: 3 | L43: 3 | M43: 4 | N43: 4 | O43: 5 | P43: 6 | Q43: 6 | R43: 6 | S43: 7 | T43: 7 | U43: 7 | V43: 8 | W43: 8 | X43: 8 | Y43: 9 | Z43: 11 | AA43: 8 | AB43: 6 | AC43: 6 | AD43: 6 | AE43: 6 | AF43: 6 | AG43: 5 | AH43: 5 | AI43: 5 | AJ43: 4 | AK43: 3 | AL43: 3
A44: ARR | C44: =C42*Assumptions!$B$17 -> 0 | D44: =D42*Assumptions!$B$17 -> 0 | E44: =E42*Assumptions!$B$17 -> 0 | F44: =F42*Assumptions!$B$17 -> 0 | G44: =G42*Assumptions!$B$17 -> 0 | H44: =H42*Assumptions!$B$17 -> 179200 | I44: =I42*Assumptions!$B$17 -> 313600 | J44: =J42*Assumptions!$B$17 -> 448000 | ... AL44: =AL42*Assumptions!$B$17 -> 7840000
A45: MRR | C45: =C44/12 -> 0 | D45: =D44/12 -> 0 | E45: =E44/12 -> 0 | F45: =F44/12 -> 0 | G45: =G44/12 -> 0 | H45: =H44/12 -> 14933.333 | I45: =I44/12 -> 26133.333 | J45: =J44/12 -> 37333.333 | ... AL45: =AL44/12 -> 653333.33

Sheet Annual Summary
A1: BRICLY — ANNUAL P&L SUMMARY (high-ticket model)
A3: Metric | B3: Year 1 | C3: Year 2 | D3: Year 3 | E3: 3-Year Total
A4: Gross Revenue | B4: =SUM('P&L Monthly'!C4:N4) -> 350933.33 | C4: =SUM('P&L Monthly'!O4:Z4) -> 2986666.7 | D4: =SUM('P&L Monthly'!AA4:AL4) -> 6742400 | E4: =SUM(B4:D4) -> 10080000
A5: Total COGS | B5: =SUM('P&L Monthly'!C8:N8) -> -54097 | C5: =SUM('P&L Monthly'!O8:Z8) -> -460400 | D5: =SUM('P&L Monthly'!AA8:AL8) -> -1039353 | E5: =SUM(B5:D5) -> -1553850
A6: Gross Profit | B6: =SUM('P&L Monthly'!C9:N9) -> 296836.33 | C6: =SUM('P&L Monthly'!O9:Z9) -> 2526266.7 | D6: =SUM('P&L Monthly'!AA9:AL9) -> 5703047 | E6: =SUM(B6:D6) -> 8526150
A7: Total Payroll | B7: =SUM('P&L Monthly'!C24:N24) -> -288633 | C7: =SUM('P&L Monthly'!O24:Z24) -> -512753 | D7: =SUM('P&L Monthly'!AA24:AL24) -> -632352 | E7: =SUM(B7:D7) -> -1433738
A8: Total Opex | B8: =SUM('P&L Monthly'!C33:N33) -> -52264 | C8: =SUM('P&L Monthly'!O33:Z33) -> -182200 | D8: =SUM('P&L Monthly'!AA33:AL33) -> -352536 | E8: =SUM(B8:D8) -> -587000
A9: Total Costs | B9: =SUM('P&L Monthly'!C36:N36) -> -340897 | C9: =SUM('P&L Monthly'!O36:Z36) -> -694953 | D9: =SUM('P&L Monthly'!AA36:AL36) -> -984888 | E9: =SUM(B9:D9) -> -2020738
A10: EBITDA | B10: =SUM('P&L Monthly'!C37:N37) -> -44060.667 | C10: =SUM('P&L Monthly'!O37:Z37) -> 1831313.7 | D10: =SUM('P&L Monthly'!AA37:AL37) -> 4718159 | E10: =SUM(B10:D10) -> 6505412
A11: EBITDA margin | B11: =B10/B4 -> -0.12555281 | C11: =C10/C4 -> 0.61316306 | D11: =D10/D4 -> 0.69977441 | E11: =E10/E4 -> 0.64537817
A13: YEAR-END POSITION
A14: Active customers (year-end) | B14: ='P&L Monthly'!N42 -> 24 | C14: ='P&L Monthly'!Z42 -> 112 | D14: ='P&L Monthly'!AL42 -> 175
A15: ARR (year-end) | B15: ='P&L Monthly'!N44 -> 1075200 | C15: ='P&L Monthly'!Z44 -> 5017600 | D15: ='P&L Monthly'!AL44 -> 7840000
A16: MRR (year-end) | B16: ='P&L Monthly'!N45 -> 89600 | C16: ='P&L Monthly'!Z45 -> 418133.33 | D16: ='P&L Monthly'!AL45 -> 653333.33
A17: Cumulative cash (year-end) | B17: ='P&L Monthly'!N39 -> -44060.667 | C17: ='P&L Monthly'!Z39 -> 1787253 | D17: ='P&L Monthly'!AL39 -> 6505412
A19: Note: Gross Profit = Net Revenue after all COGS (generation + AI layer + infra + payments).

Sheet Investment Summary
A1: BRICLY — INVESTOR SUMMARY (high-ticket pricing)
A3: THE OPPORTUNITY
A4: Company | B4: Bricly Ltd — Malta (EU)
A5: Product | B5: AI marketing + sales platform for off-plan developers
A6: Pricing model | B6: High-ticket, demo-gated, annual | C6: Platform license + per-development + per-unit
A7: Blended ACV | B7: =Assumptions!B17 -> 44800
A8: Blended gross margin | B8: =Assumptions!B25 -> 0.84584821 | C8: After generation + AI layer + infra + payments
A10: UNIT ECONOMICS
A11: CAC (blended) | B11: =Assumptions!B29 -> 6000 | C11: Demo-gated enterprise motion
A12: Payback period | B12: =Assumptions!B31 -> 1.9000369 | C12: Months
A13: LTV | B13: =Assumptions!B34 -> 210522.22
A14: LTV : CAC | B14: =Assumptions!B35 -> 35.087037 | C14: >10x world-class
A16: FINANCIAL PROJECTIONS
A17: Year 1 Gross Revenue | B17: ='Annual Summary'!B4 -> 350933.33
A18: Year 2 Gross Revenue | B18: ='Annual Summary'!C4 -> 2986666.7
A19: Year 3 Gross Revenue | B19: ='Annual Summary'!D4 -> 6742400
A20: ARR — end of Year 2 | B20: ='Annual Summary'!C15 -> 5017600 | C20: €5M ARR milestone
A21: ARR — end of Year 3 | B21: ='Annual Summary'!D15 -> 7840000
A22: Active customers — end Y3 | B22: ='Annual Summary'!D14 -> 175 | C22: vs 985 on the old volume model
A23: Year 3 EBITDA | B23: ='Annual Summary'!D10 -> 4718159
A24: Year 3 EBITDA margin | B24: ='Annual Summary'!D11 -> 0.69977441
A26: THE SHIFT FROM THE OLD MODEL
A27: Old model: €99 base + €5/unit/mo, ~€15.4k blended ACV, 985 clients for ~€6.1M ARR.
A28: New model: ~€44.8k blended ACV, ~112 customers for €5M ARR. Same revenue, ~1/9th the customers.
A29: ARR composition: platform licenses are hard recurring (~22%); per-dev and per-unit recur with launch cadence.
A31: Worst cumulative cash position | B31: -137985 | C31: Trough at month 7 (build phase)
A32: Pre-seed raised (friends & family) | B32: 300000 | C32: Covers the build-phase trough with buffer
